setup.py
smklog/__init__.py
smklog/logger.py
smklog.egg-info/PKG-INFO
smklog.egg-info/SOURCES.txt
smklog.egg-info/dependency_links.txt
smklog.egg-info/requires.txt
smklog.egg-info/top_level.txt
tests/__init__.py
tests/test_smklog.py