Metadata-Version: 2.1
Name: smklog
Version: 1.1.3
Summary: Samarkand logger
Home-page: https://gitlab.com/samarkand-util/smklog
Author: David Chen
Author-email: david.chen@samarkand.global
License: UNKNOWN
Keywords: logger
Platform: UNKNOWN
